{
  "diffEditor.ignoreTrimWhitespace": false,
  "editor.fontFamily": "Martian Mono",
  "editor.fontSize": 11,
  "editor.minimap.enabled": false,
  "editor.occurrencesHighlight": "off",
  // "editor.quickSuggestions": {
  //   "comments": false,
  //   "other": false,
  //   "strings": false
  // },
  "editor.rulers": [120],
  "editor.selectionHighlight": false,
  // "editor.suggestOnTriggerCharacters": false,
  "editor.tabCompletion": "on",
  "editor.tabSize": 2,
  "explorer.confirmDelete": false,
  "extensions.ignoreRecommendations": true,
  "files.insertFinalNewline": true,
  "files.trimTrailingWhitespace": true,
  "git.autofetch": true,
  "git.confirmSync": false,
  "git.ignoreMissingGitWarning": true,
  "git.openRepositoryInParentFolders": "always",
  // "security.workspace.trust.untrustedFiles": "open",
  // "window.menuBarVisibility": "compact",
  "window.titleBarStyle": "custom",
  "workbench.colorTheme": "Visual Studio Dark",
  "workbench.iconTheme": "material-icon-theme"
}
